數位系統實習/LAB6/LAB6_1/LAB6_1.v
//8位元移位暫存器
module LAB6_1 (
    input clk,
    input [1:0] sel,
    input [7:0] in,
    output reg [7:0] out
);

    initial begin
        out = 8'b00000000;
    end

    always @(posedge clk) begin
        case (sel)
            2'b00: out <= in;              
            2'b01: out <= {3'b000, out[7:3]}; 
            2'b10: out <= {2'b00, out[7:2]}; 
            2'b11: out <= {1'b0, out[7:1]};              
            default: out <= 8'bxxxxxxx; 
        endcase
    end

endmodule //LAB6_1

數位系統實習/LAB6/LAB6_1/t_LAB6_1.v
`include "數位系統實習/LAB6/LAB6_1/LAB6_1.v"
`timescale 1ps/1ps


module t_LAB6_1;
    
    reg clk;
    reg [7:0] in;
    reg [1:0] sel;
    // wires                                               
    wire [7:0] out;

    // assign statements (if any)                          
    LAB6_1 i1 (
    // port map - connection between master ports and signals/registers   
        .clk(clk),
        .in(in),
        .out(out),
        .sel(sel)
    );
    initial 

    begin 
    #200000 $finish;
    end 

    // clk
    always
    begin
        clk = 1'b0;
        clk = #10000 1'b1;
        #10000;
    end 
    // in[ 7 ]
    initial
    begin
        in[7] = 1'b0;
        in[7] = #40000 1'b1;
    end 
    // in[ 6 ]
    initial
    begin
        in[6] = 1'b0;
    end 
    // in[ 5 ]
    initial
    begin
        in[5] = 1'b0;
        in[5] = #40000 1'b1;
    end 
    // in[ 4 ]
    initial
    begin
        in[4] = 1'b0;
        in[4] = #40000 1'b1;
    end 
    // in[ 3 ]
    initial
    begin
        in[3] = 1'b0;
        in[3] = #40000 1'b1;
    end 
    // in[ 2 ]
    initial
    begin
        in[2] = 1'b0;
    end 
    // in[ 1 ]
    initial
    begin
        in[1] = 1'b0;
        in[1] = #40000 1'b1;
    end 
    // in[ 0 ]
    initial
    begin
        in[0] = 1'b0;
    end 
    // sel[ 1 ]
    initial
    begin
        sel[1] = 1'b0;
        sel[1] = #60000 1'b1;
        sel[1] = #20000 1'b0;
        sel[1] = #20000 1'b1;
        sel[1] = #20000 1'b0;
    end 
    // sel[ 0 ]
    initial
    begin
        sel[0] = 1'b0;
        sel[0] = #60000 1'b1;
        sel[0] = #20000 1'b0;
        sel[0] = #80000 1'b1;
        sel[0] = #20000 1'b0;
    end 

    initial begin
        $dumpfile("LAB6_1.vcd");
        $dumpvars(0, t_LAB6_1);
    end

endmodule

數位系統實習/LAB6/LAB6_1/LAB6_1.vcd
$date
	Wed Oct  8 23:09:22 2025
$end
$version
	Icarus Verilog
$end
$timescale
	1ps
$end
$scope module t_LAB6_1 $end
$var wire 8 ! out [7:0] $end
$var reg 1 " clk $end
$var reg 8 # in [7:0] $end
$var reg 2 $ sel [1:0] $end
$scope module i1 $end
$var wire 1 " clk $end
$var wire 8 % in [7:0] $end
$var wire 2 & sel [1:0] $end
$var reg 8 ' out [7:0] $end
$upscope $end
$upscope $end
$enddefinitions $end
$comment Show the parameter values. $end
$dumpall
$end
#0
$dumpvars
b0 '
b0 &
b0 %
b0 $
b0 #
0"
b0 !
$end
#10000
1"
#20000
0"
#30000
1"
#40000
0"
b10111010 #
b10111010 %
#50000
b10111010 !
b10111010 '
1"
#60000
0"
b11 $
b11 &
#70000
b1011101 !
b1011101 '
1"
#80000
0"
b0 $
b0 &
#90000
b10111010 !
b10111010 '
1"
#100000
0"
b10 $
b10 &
#110000
b101110 !
b101110 '
1"
#120000
0"
b0 $
b0 &
#130000
b10111010 !
b10111010 '
1"
#140000
0"
#150000
1"
#160000
0"
b1 $
b1 &
#170000
b10111 !
b10111 '
1"
#180000
0"
b0 $
b0 &
#190000
b10111010 !
b10111010 '
1"
