數位邏輯/johnson_counter/johhnson_counter.v
module counter(output s0,s1,s2,s3,s4,s5,s6,s7, input clk,clear);
DFF M0(A,clk,clear,!E);
DFF M1(B,clk,clear,A);
DFF M2(C,clk,clear,B);
DFF M3(E,clk,clear,C);
and(s0,!A,!E);
and(s1,A,!B);
and(s2,B,!C);
and(s3,C,!E);
and(s4,E,A);
and(s5,!A,B);
and(s6,!B,C);
and(s7,!C,E);
endmodule
module DFF(output reg Q,input clk,clear,D);
always@(posedge clk,negedge clear)
if(clear==1'b0)
Q<=1'b0;else Q<=D;
endmodule
module test();
wire s0,s1,s2,s3,s4,s5,s6,s7;
reg clk,clear;
counter M0(s0,s1,s2,s3,s4,s5,s6,s7,clk,clear);
initial #400 $finish;
initial begin clk=1'b0;forever #5clk=!clk;end
initial fork
clear=1'b0;
#5clear=1'b1;
#200clear =1'b0;
#240clear=1'b1;
$dumpfile("dump.vcd");
$dumpvars(0,test);
join
endmodule

數位邏輯/johnson_counter/dump.vcd
$date
	Sun Dec 18 13:38:35 2022
$end
$version
	Icarus Verilog
$end
$timescale
	1s
$end
$scope module test $end
$var wire 1 ! s0 $end
$var wire 1 " s1 $end
$var wire 1 # s2 $end
$var wire 1 $ s3 $end
$var wire 1 % s4 $end
$var wire 1 & s5 $end
$var wire 1 ' s6 $end
$var wire 1 ( s7 $end
$var reg 1 ) clear $end
$var reg 1 * clk $end
$scope module M0 $end
$var wire 1 + A $end
$var wire 1 , B $end
$var wire 1 - C $end
$var wire 1 . E $end
$var wire 1 / clear $end
$var wire 1 0 clk $end
$var wire 1 ! s0 $end
$var wire 1 " s1 $end
$var wire 1 # s2 $end
$var wire 1 $ s3 $end
$var wire 1 % s4 $end
$var wire 1 & s5 $end
$var wire 1 ' s6 $end
$var wire 1 ( s7 $end
$scope module M0 $end
$var wire 1 1 D $end
$var wire 1 / clear $end
$var wire 1 0 clk $end
$var reg 1 2 Q $end
$upscope $end
$scope module M1 $end
$var wire 1 + D $end
$var wire 1 / clear $end
$var wire 1 0 clk $end
$var reg 1 3 Q $end
$upscope $end
$scope module M2 $end
$var wire 1 , D $end
$var wire 1 / clear $end
$var wire 1 0 clk $end
$var reg 1 4 Q $end
$upscope $end
$scope module M3 $end
$var wire 1 - D $end
$var wire 1 / clear $end
$var wire 1 0 clk $end
$var reg 1 5 Q $end
$upscope $end
$upscope $end
$upscope $end
$enddefinitions $end
#0
$dumpvars
05
04
03
02
11
00
0/
0.
0-
0,
0+
0*
0)
0(
0'
0&
0%
0$
0#
0"
1!
$end
#5
0!
1"
12
1+
1)
1/
1*
10
#10
0*
00
#15
0"
1#
13
1,
1*
10
#20
0*
00
#25
0#
1$
14
1-
1*
10
#30
0*
00
#35
0$
1%
15
01
1.
1*
10
#40
0*
00
#45
1&
0%
02
0+
1*
10
#50
0*
00
#55
1'
0&
03
0,
1*
10
#60
0*
00
#65
1(
0'
04
0-
1*
10
#70
0*
00
#75
1!
0(
05
11
0.
1*
10
#80
0*
00
#85
0!
1"
12
1+
1*
10
#90
0*
00
#95
0"
1#
13
1,
1*
10
#100
0*
00
#105
0#
1$
14
1-
1*
10
#110
0*
00
#115
0$
1%
15
01
1.
1*
10
#120
0*
00
#125
1&
0%
02
0+
1*
10
#130
0*
00
#135
1'
0&
03
0,
1*
10
#140
0*
00
#145
1(
0'
04
0-
1*
10
#150
0*
00
#155
1!
0(
05
11
0.
1*
10
#160
0*
00
#165
0!
1"
12
1+
1*
10
#170
0*
00
#175
0"
1#
13
1,
1*
10
#180
0*
00
#185
0#
1$
14
1-
1*
10
#190
0*
00
#195
0$
1%
15
01
1.
1*
10
#200
1!
0%
05
11
0.
04
0-
03
0,
02
0+
0*
00
0)
0/
#205
1*
10
#210
0*
00
#215
1*
10
#220
0*
00
#225
1*
10
#230
0*
00
#235
1*
10
#240
0*
00
1)
1/
#245
0!
1"
12
1+
1*
10
#250
0*
00
#255
0"
1#
13
1,
1*
10
#260
0*
00
#265
0#
1$
14
1-
1*
10
#270
0*
00
#275
0$
1%
15
01
1.
1*
10
#280
0*
00
#285
1&
0%
02
0+
1*
10
#290
0*
00
#295
1'
0&
03
0,
1*
10
#300
0*
00
#305
1(
0'
04
0-
1*
10
#310
0*
00
#315
1!
0(
05
11
0.
1*
10
#320
0*
00
#325
0!
1"
12
1+
1*
10
#330
0*
00
#335
0"
1#
13
1,
1*
10
#340
0*
00
#345
0#
1$
14
1-
1*
10
#350
0*
00
#355
0$
1%
15
01
1.
1*
10
#360
0*
00
#365
1&
0%
02
0+
1*
10
#370
0*
00
#375
1'
0&
03
0,
1*
10
#380
0*
00
#385
1(
0'
04
0-
1*
10
#390
0*
00
#395
1!
0(
05
11
0.
1*
10
