數位系統設計/lab1_2/lab1_2.v
module lab1_2 (
    input clk,
    input [7:0] accum,data,
    input [2:0] opcode,
    output reg [7:0] alu_out
);

initial begin
    alu_out=8'b0;
end

always@(posedge clk)begin
    case(opcode)
        3'b000:alu_out<=accum;//pass accum
        3'b001:alu_out<=accum+data;//add
        3'b010:alu_out<=accum-data;//sub
        3'b011:alu_out<=accum&data;//and
        3'b100:alu_out<=accum^data;//xor
        3'b101:alu_out<=~accum+1;//2's complement
        3'b110:alu_out<=accum*5+accum/8;//accum*5 + accum/8
        3'b111:alu_out<= (accum>=32) ? data:~data;//if (accum >>= 32), alu_out = data,else alu_out = 1 s complement of data
        default:alu_out<=8'bx;
    endcase
end

endmodule //lab1_2

數位系統設計/lab1_2/t_lab2.v
`include "lab1_2/lab1_2.v"
`timescale 1us/1ns
module t_lab2 ();
reg clk;
reg [7:0] accum,data;
reg [2:0] opcode;
wire [7:0] alu_out;
lab1_2 U_lab1_2 (
    .clk(clk),
    .accum(accum),
    .data(data),
    .opcode(opcode),
    .alu_out(alu_out)
);

initial begin 
    #1000 $finish;
end

//clk
initial begin
    clk=0;
    forever #5clk=~clk;
end
//counter
initial begin
    accum=8'b0;
    data=8'b0;
    opcode=3'b0;
    forever #10 begin
        accum<=accum+8'b1;
        data<=data+8'b1;
        opcode<=opcode+3'b1;
    end
end

initial begin
    $dumpfile("t_lab2.vcd");
    $dumpvars(0,t_lab2);
end

endmodule //t_lab2

數位系統設計/build/t_lab2.vcd
$date
	Mon Oct 20 01:10:22 2025
$end
$version
	Icarus Verilog
$end
$timescale
	1ns
$end
$scope module t_lab2 $end
$var wire 8 ! alu_out [7:0] $end
$var reg 8 " accum [7:0] $end
$var reg 1 # clk $end
$var reg 8 $ data [7:0] $end
$var reg 3 % opcode [2:0] $end
$scope module U_lab1_2 $end
$var wire 8 & accum [7:0] $end
$var wire 1 # clk $end
$var wire 8 ' data [7:0] $end
$var wire 3 ( opcode [2:0] $end
$var reg 8 ) alu_out [7:0] $end
$upscope $end
$upscope $end
$enddefinitions $end
$comment Show the parameter values. $end
$dumpall
$end
#0
$dumpvars
b0 )
b0 (
b0 '
b0 &
b0 %
b0 $
0#
b0 "
b0 !
$end
#5000
1#
#10000
b1 %
b1 (
b1 $
b1 '
b1 "
b1 &
0#
#15000
b10 !
b10 )
1#
#20000
b10 %
b10 (
b10 $
b10 '
b10 "
b10 &
0#
#25000
b0 !
b0 )
1#
#30000
b11 %
b11 (
b11 $
b11 '
b11 "
b11 &
0#
#35000
b11 !
b11 )
1#
#40000
b100 %
b100 (
b100 $
b100 '
b100 "
b100 &
0#
#45000
b0 !
b0 )
1#
#50000
b101 %
b101 (
b101 $
b101 '
b101 "
b101 &
0#
#55000
b11111011 !
b11111011 )
1#
#60000
b110 %
b110 (
b110 $
b110 '
b110 "
b110 &
0#
#65000
b11110 !
b11110 )
1#
#70000
b111 %
b111 (
b111 $
b111 '
b111 "
b111 &
0#
#75000
b11111000 !
b11111000 )
1#
#80000
b0 %
b0 (
b1000 $
b1000 '
b1000 "
b1000 &
0#
#85000
b1000 !
b1000 )
1#
#90000
b1 %
b1 (
b1001 $
b1001 '
b1001 "
b1001 &
0#
#95000
b10010 !
b10010 )
1#
#100000
b10 %
b10 (
b1010 $
b1010 '
b1010 "
b1010 &
0#
#105000
b0 !
b0 )
1#
#110000
b11 %
b11 (
b1011 $
b1011 '
b1011 "
b1011 &
0#
#115000
b1011 !
b1011 )
1#
#120000
b100 %
b100 (
b1100 $
b1100 '
b1100 "
b1100 &
0#
#125000
b0 !
b0 )
1#
#130000
b101 %
b101 (
b1101 $
b1101 '
b1101 "
b1101 &
0#
#135000
b11110011 !
b11110011 )
1#
#140000
b110 %
b110 (
b1110 $
b1110 '
b1110 "
b1110 &
0#
#145000
b1000111 !
b1000111 )
1#
#150000
b111 %
b111 (
b1111 $
b1111 '
b1111 "
b1111 &
0#
#155000
b11110000 !
b11110000 )
1#
#160000
b0 %
b0 (
b10000 $
b10000 '
b10000 "
b10000 &
0#
#165000
b10000 !
b10000 )
1#
#170000
b1 %
b1 (
b10001 $
b10001 '
b10001 "
b10001 &
0#
#175000
b100010 !
b100010 )
1#
#180000
b10 %
b10 (
b10010 $
b10010 '
b10010 "
b10010 &
0#
#185000
b0 !
b0 )
1#
#190000
b11 %
b11 (
b10011 $
b10011 '
b10011 "
b10011 &
0#
#195000
b10011 !
b10011 )
1#
#200000
b100 %
b100 (
b10100 $
b10100 '
b10100 "
b10100 &
0#
#205000
b0 !
b0 )
1#
#210000
b101 %
b101 (
b10101 $
b10101 '
b10101 "
b10101 &
0#
#215000
b11101011 !
b11101011 )
1#
#220000
b110 %
b110 (
b10110 $
b10110 '
b10110 "
b10110 &
0#
#225000
b1110000 !
b1110000 )
1#
#230000
b111 %
b111 (
b10111 $
b10111 '
b10111 "
b10111 &
0#
#235000
b11101000 !
b11101000 )
1#
#240000
b0 %
b0 (
b11000 $
b11000 '
b11000 "
b11000 &
0#
#245000
b11000 !
b11000 )
1#
#250000
b1 %
b1 (
b11001 $
b11001 '
b11001 "
b11001 &
0#
#255000
b110010 !
b110010 )
1#
#260000
b10 %
b10 (
b11010 $
b11010 '
b11010 "
b11010 &
0#
#265000
b0 !
b0 )
1#
#270000
b11 %
b11 (
b11011 $
b11011 '
b11011 "
b11011 &
0#
#275000
b11011 !
b11011 )
1#
#280000
b100 %
b100 (
b11100 $
b11100 '
b11100 "
b11100 &
0#
#285000
b0 !
b0 )
1#
#290000
b101 %
b101 (
b11101 $
b11101 '
b11101 "
b11101 &
0#
#295000
b11100011 !
b11100011 )
1#
#300000
b110 %
b110 (
b11110 $
b11110 '
b11110 "
b11110 &
0#
#305000
b10011001 !
b10011001 )
1#
#310000
b111 %
b111 (
b11111 $
b11111 '
b11111 "
b11111 &
0#
#315000
b11100000 !
b11100000 )
1#
#320000
b0 %
b0 (
b100000 $
b100000 '
b100000 "
b100000 &
0#
#325000
b100000 !
b100000 )
1#
#330000
b1 %
b1 (
b100001 $
b100001 '
b100001 "
b100001 &
0#
#335000
b1000010 !
b1000010 )
1#
#340000
b10 %
b10 (
b100010 $
b100010 '
b100010 "
b100010 &
0#
#345000
b0 !
b0 )
1#
#350000
b11 %
b11 (
b100011 $
b100011 '
b100011 "
b100011 &
0#
#355000
b100011 !
b100011 )
1#
#360000
b100 %
b100 (
b100100 $
b100100 '
b100100 "
b100100 &
0#
#365000
b0 !
b0 )
1#
#370000
b101 %
b101 (
b100101 $
b100101 '
b100101 "
b100101 &
0#
#375000
b11011011 !
b11011011 )
1#
#380000
b110 %
b110 (
b100110 $
b100110 '
b100110 "
b100110 &
0#
#385000
b11000010 !
b11000010 )
1#
#390000
b111 %
b111 (
b100111 $
b100111 '
b100111 "
b100111 &
0#
#395000
b100111 !
b100111 )
1#
#400000
b0 %
b0 (
b101000 $
b101000 '
b101000 "
b101000 &
0#
#405000
b101000 !
b101000 )
1#
#410000
b1 %
b1 (
b101001 $
b101001 '
b101001 "
b101001 &
0#
#415000
b1010010 !
b1010010 )
1#
#420000
b10 %
b10 (
b101010 $
b101010 '
b101010 "
b101010 &
0#
#425000
b0 !
b0 )
1#
#430000
b11 %
b11 (
b101011 $
b101011 '
b101011 "
b101011 &
0#
#435000
b101011 !
b101011 )
1#
#440000
b100 %
b100 (
b101100 $
b101100 '
b101100 "
b101100 &
0#
#445000
b0 !
b0 )
1#
#450000
b101 %
b101 (
b101101 $
b101101 '
b101101 "
b101101 &
0#
#455000
b11010011 !
b11010011 )
1#
#460000
b110 %
b110 (
b101110 $
b101110 '
b101110 "
b101110 &
0#
#465000
b11101011 !
b11101011 )
1#
#470000
b111 %
b111 (
b101111 $
b101111 '
b101111 "
b101111 &
0#
#475000
b101111 !
b101111 )
1#
#480000
b0 %
b0 (
b110000 $
b110000 '
b110000 "
b110000 &
0#
#485000
b110000 !
b110000 )
1#
#490000
b1 %
b1 (
b110001 $
b110001 '
b110001 "
b110001 &
0#
#495000
b1100010 !
b1100010 )
1#
#500000
b10 %
b10 (
b110010 $
b110010 '
b110010 "
b110010 &
0#
#505000
b0 !
b0 )
1#
#510000
b11 %
b11 (
b110011 $
b110011 '
b110011 "
b110011 &
0#
#515000
b110011 !
b110011 )
1#
#520000
b100 %
b100 (
b110100 $
b110100 '
b110100 "
b110100 &
0#
#525000
b0 !
b0 )
1#
#530000
b101 %
b101 (
b110101 $
b110101 '
b110101 "
b110101 &
0#
#535000
b11001011 !
b11001011 )
1#
#540000
b110 %
b110 (
b110110 $
b110110 '
b110110 "
b110110 &
0#
#545000
b10100 !
b10100 )
1#
#550000
b111 %
b111 (
b110111 $
b110111 '
b110111 "
b110111 &
0#
#555000
b110111 !
b110111 )
1#
#560000
b0 %
b0 (
b111000 $
b111000 '
b111000 "
b111000 &
0#
#565000
b111000 !
b111000 )
1#
#570000
b1 %
b1 (
b111001 $
b111001 '
b111001 "
b111001 &
0#
#575000
b1110010 !
b1110010 )
1#
#580000
b10 %
b10 (
b111010 $
b111010 '
b111010 "
b111010 &
0#
#585000
b0 !
b0 )
1#
#590000
b11 %
b11 (
b111011 $
b111011 '
b111011 "
b111011 &
0#
#595000
b111011 !
b111011 )
1#
#600000
b100 %
b100 (
b111100 $
b111100 '
b111100 "
b111100 &
0#
#605000
b0 !
b0 )
1#
#610000
b101 %
b101 (
b111101 $
b111101 '
b111101 "
b111101 &
0#
#615000
b11000011 !
b11000011 )
1#
#620000
b110 %
b110 (
b111110 $
b111110 '
b111110 "
b111110 &
0#
#625000
b111101 !
b111101 )
1#
#630000
b111 %
b111 (
b111111 $
b111111 '
b111111 "
b111111 &
0#
#635000
b111111 !
b111111 )
1#
#640000
b0 %
b0 (
b1000000 $
b1000000 '
b1000000 "
b1000000 &
0#
#645000
b1000000 !
b1000000 )
1#
#650000
b1 %
b1 (
b1000001 $
b1000001 '
b1000001 "
b1000001 &
0#
#655000
b10000010 !
b10000010 )
1#
#660000
b10 %
b10 (
b1000010 $
b1000010 '
b1000010 "
b1000010 &
0#
#665000
b0 !
b0 )
1#
#670000
b11 %
b11 (
b1000011 $
b1000011 '
b1000011 "
b1000011 &
0#
#675000
b1000011 !
b1000011 )
1#
#680000
b100 %
b100 (
b1000100 $
b1000100 '
b1000100 "
b1000100 &
0#
#685000
b0 !
b0 )
1#
#690000
b101 %
b101 (
b1000101 $
b1000101 '
b1000101 "
b1000101 &
0#
#695000
b10111011 !
b10111011 )
1#
#700000
b110 %
b110 (
b1000110 $
b1000110 '
b1000110 "
b1000110 &
0#
#705000
b1100110 !
b1100110 )
1#
#710000
b111 %
b111 (
b1000111 $
b1000111 '
b1000111 "
b1000111 &
0#
#715000
b1000111 !
b1000111 )
1#
#720000
b0 %
b0 (
b1001000 $
b1001000 '
b1001000 "
b1001000 &
0#
#725000
b1001000 !
b1001000 )
1#
#730000
b1 %
b1 (
b1001001 $
b1001001 '
b1001001 "
b1001001 &
0#
#735000
b10010010 !
b10010010 )
1#
#740000
b10 %
b10 (
b1001010 $
b1001010 '
b1001010 "
b1001010 &
0#
#745000
b0 !
b0 )
1#
#750000
b11 %
b11 (
b1001011 $
b1001011 '
b1001011 "
b1001011 &
0#
#755000
b1001011 !
b1001011 )
1#
#760000
b100 %
b100 (
b1001100 $
b1001100 '
b1001100 "
b1001100 &
0#
#765000
b0 !
b0 )
1#
#770000
b101 %
b101 (
b1001101 $
b1001101 '
b1001101 "
b1001101 &
0#
#775000
b10110011 !
b10110011 )
1#
#780000
b110 %
b110 (
b1001110 $
b1001110 '
b1001110 "
b1001110 &
0#
#785000
b10001111 !
b10001111 )
1#
#790000
b111 %
b111 (
b1001111 $
b1001111 '
b1001111 "
b1001111 &
0#
#795000
b1001111 !
b1001111 )
1#
#800000
b0 %
b0 (
b1010000 $
b1010000 '
b1010000 "
b1010000 &
0#
#805000
b1010000 !
b1010000 )
1#
#810000
b1 %
b1 (
b1010001 $
b1010001 '
b1010001 "
b1010001 &
0#
#815000
b10100010 !
b10100010 )
1#
#820000
b10 %
b10 (
b1010010 $
b1010010 '
b1010010 "
b1010010 &
0#
#825000
b0 !
b0 )
1#
#830000
b11 %
b11 (
b1010011 $
b1010011 '
b1010011 "
b1010011 &
0#
#835000
b1010011 !
b1010011 )
1#
#840000
b100 %
b100 (
b1010100 $
b1010100 '
b1010100 "
b1010100 &
0#
#845000
b0 !
b0 )
1#
#850000
b101 %
b101 (
b1010101 $
b1010101 '
b1010101 "
b1010101 &
0#
#855000
b10101011 !
b10101011 )
1#
#860000
b110 %
b110 (
b1010110 $
b1010110 '
b1010110 "
b1010110 &
0#
#865000
b10111000 !
b10111000 )
1#
#870000
b111 %
b111 (
b1010111 $
b1010111 '
b1010111 "
b1010111 &
0#
#875000
b1010111 !
b1010111 )
1#
#880000
b0 %
b0 (
b1011000 $
b1011000 '
b1011000 "
b1011000 &
0#
#885000
b1011000 !
b1011000 )
1#
#890000
b1 %
b1 (
b1011001 $
b1011001 '
b1011001 "
b1011001 &
0#
#895000
b10110010 !
b10110010 )
1#
#900000
b10 %
b10 (
b1011010 $
b1011010 '
b1011010 "
b1011010 &
0#
#905000
b0 !
b0 )
1#
#910000
b11 %
b11 (
b1011011 $
b1011011 '
b1011011 "
b1011011 &
0#
#915000
b1011011 !
b1011011 )
1#
#920000
b100 %
b100 (
b1011100 $
b1011100 '
b1011100 "
b1011100 &
0#
#925000
b0 !
b0 )
1#
#930000
b101 %
b101 (
b1011101 $
b1011101 '
b1011101 "
b1011101 &
0#
#935000
b10100011 !
b10100011 )
1#
#940000
b110 %
b110 (
b1011110 $
b1011110 '
b1011110 "
b1011110 &
0#
#945000
b11100001 !
b11100001 )
1#
#950000
b111 %
b111 (
b1011111 $
b1011111 '
b1011111 "
b1011111 &
0#
#955000
b1011111 !
b1011111 )
1#
#960000
b0 %
b0 (
b1100000 $
b1100000 '
b1100000 "
b1100000 &
0#
#965000
b1100000 !
b1100000 )
1#
#970000
b1 %
b1 (
b1100001 $
b1100001 '
b1100001 "
b1100001 &
0#
#975000
b11000010 !
b11000010 )
1#
#980000
b10 %
b10 (
b1100010 $
b1100010 '
b1100010 "
b1100010 &
0#
#985000
b0 !
b0 )
1#
#990000
b11 %
b11 (
b1100011 $
b1100011 '
b1100011 "
b1100011 &
0#
#995000
b1100011 !
b1100011 )
1#
#1000000
b100 %
b100 (
b1100100 $
b1100100 '
b1100100 "
b1100100 &
0#
