數位系統實習/LAB7/LAB7_3/LAB7_3.v
module LAB7_3 #(parameter shift_size = 8)(
    input  [7:0] in,
    output reg [3:0] hunds, tens, ones
);
    integer i;
    reg [7:0] bin;
    
    always @(*) begin
        bin   = in;
        hunds = 0;
        tens  = 0;
        ones  = 0;
        for (i = 0; i < shift_size; i = i + 1) begin
            if (hunds >= 5)
                hunds = hunds + 3;
            if (tens >= 5)
                tens = tens + 3;
            if (ones >= 5)
                ones = ones + 3;
            {hunds, tens, ones, bin} = {hunds, tens, ones, bin} << 1;
        end
    end
endmodule

// --------------------------------------------------------------------
// module LAB7_3 #(parameter shift_size=8)(
//     input [7:0] in,
//     output reg [3:0] hunds, tens, ones
// );
//     integer i;
//     reg [19:0] temp;
//     always @(*) begin
//         temp = 0;
//         temp[7:0] = in;
//         for (i = 0; i < shift_size; i = i + 1) begin
//             if (temp[11:8] >= 5)
//                 temp[11:8] = temp[11:8] + 3;
//             if (temp[15:12] >= 5)
//                 temp[15:12] = temp[15:12] + 3;
//             if (temp[19:16] >= 5)
//                 temp[19:16] = temp[19:16] + 3;
//             temp = temp << 1;
//         end
//         ones  = temp[11:8];
//         tens  = temp[15:12];
//         hunds = temp[19:16];
//     end

// endmodule //LAB7_3

數位系統實習/LAB7/LAB7_3/t_LAB7_3.v
`include "數位系統實習/LAB7/LAB7_3/LAB7_3.v"
`timescale 1ps/1ps

module t_LAB7_3;
// constants                                           
// general purpose registers
reg [7:0] in;
// wires                                               
wire [3:0] hunds;
wire [3:0] ones;
wire [3:0] tens;

// assign statements (if any)                          
LAB7_3 i1 (
// port map - connection between master ports and signals/registers   
	.hunds(hunds),
	.in(in),
	.ones(ones),
	.tens(tens)
);
initial 
begin 
#200000 $stop;
end 
// in[ 7 ]
initial
begin
	in[7] = 1'b1;
end 
// in[ 6 ]
initial
begin
	in[6] = 1'b1;
end 
// in[ 5 ]
initial
begin
	in[5] = 1'b1;
end 
// in[ 4 ]
initial
begin
	in[4] = 1'b1;
	in[4] = #160000 1'b0;
end 
// in[ 3 ]
initial
begin
	in[3] = 1'b1;
	in[3] = #80000 1'b0;
	in[3] = #80000 1'b1;
end 
// in[ 2 ]
initial
begin
	in[2] = 1'b1;
	in[2] = #40000 1'b0;
	in[2] = #40000 1'b1;
	in[2] = #40000 1'b0;
	in[2] = #40000 1'b1;
end 
// in[ 1 ]
initial
begin
	in[1] = 1'b1;
	in[1] = #20000 1'b0;
	# 20000;
	repeat(3)
	begin
		in[1] = 1'b1;
		in[1] = #20000 1'b0;
		# 20000;
	end
	in[1] = 1'b1;
	in[1] = #20000 1'b0;
end 
// in[ 0 ]
initial
begin
	in[0] = 1'b1;
	in[0] = #10000 1'b0;
	# 10000;
	repeat(8)
	begin
		in[0] = 1'b1;
		in[0] = #10000 1'b0;
		# 10000;
	end
	in[0] = 1'b1;
	in[0] = #10000 1'b0;
end 
initial
begin
$dumpfile("t_LAB7_3.vcd");
$dumpvars(0, t_LAB7_3); 
end

endmodule

數位系統實習/LAB7/LAB7_3/t_LAB7_3.vcd
$date
	Thu Oct 16 02:18:46 2025
$end
$version
	Icarus Verilog
$end
$timescale
	1ps
$end
$scope module t_LAB7_3 $end
$var wire 4 ! tens [3:0] $end
$var wire 4 " ones [3:0] $end
$var wire 4 # hunds [3:0] $end
$var reg 8 $ in [7:0] $end
$scope module i1 $end
$var wire 8 % in [7:0] $end
$var parameter 32 & shift_size $end
$var reg 8 ' bin [7:0] $end
$var reg 4 ( hunds [3:0] $end
$var reg 4 ) ones [3:0] $end
$var reg 4 * tens [3:0] $end
$var integer 32 + i [31:0] $end
$upscope $end
$upscope $end
$enddefinitions $end
$comment Show the parameter values. $end
$dumpall
b1000 &
$end
#0
$dumpvars
b1000 +
b101 *
b101 )
b10 (
b0 '
b11111111 %
b11111111 $
b10 #
b101 "
b101 !
$end
#10000
b1000 +
b100 "
b100 )
b101 !
b101 *
b10 #
b10 (
b0 '
b11111110 $
b11111110 %
#20000
b1000 +
b11 "
b11 )
b101 !
b101 *
b10 #
b10 (
b0 '
b11111101 $
b11111101 %
#30000
b1000 +
b10 "
b10 )
b101 !
b101 *
b10 #
b10 (
b0 '
b11111100 $
b11111100 %
#40000
b1000 +
b1 "
b1 )
b101 !
b101 *
b10 #
b10 (
b0 '
b11111011 $
b11111011 %
#50000
b1000 +
b0 "
b0 )
b101 !
b101 *
b10 #
b10 (
b0 '
b11111010 $
b11111010 %
#60000
b1001 "
b1001 )
b1000 +
b100 !
b100 *
b10 #
b10 (
b0 '
b11111001 $
b11111001 %
#70000
b1000 +
b1000 "
b1000 )
b100 !
b100 *
b10 #
b10 (
b0 '
b11111000 $
b11111000 %
#80000
b1000 +
b111 "
b111 )
b100 !
b100 *
b10 #
b10 (
b0 '
b11110111 $
b11110111 %
#90000
b1000 +
b110 "
b110 )
b100 !
b100 *
b10 #
b10 (
b0 '
b11110110 $
b11110110 %
#100000
b1000 +
b101 "
b101 )
b100 !
b100 *
b10 #
b10 (
b0 '
b11110101 $
b11110101 %
#110000
b1000 +
b100 "
b100 )
b100 !
b100 *
b10 #
b10 (
b0 '
b11110100 $
b11110100 %
#120000
b1000 +
b11 "
b11 )
b100 !
b100 *
b10 #
b10 (
b0 '
b11110011 $
b11110011 %
#130000
b1000 +
b10 "
b10 )
b100 !
b100 *
b10 #
b10 (
b0 '
b11110010 $
b11110010 %
#140000
b1000 +
b1 "
b1 )
b100 !
b100 *
b10 #
b10 (
b0 '
b11110001 $
b11110001 %
#150000
b1000 +
b0 "
b0 )
b100 !
b100 *
b10 #
b10 (
b0 '
b11110000 $
b11110000 %
#160000
b1001 "
b1001 )
b1000 +
b11 !
b11 *
b10 #
b10 (
b0 '
b11101111 $
b11101111 %
#170000
b1000 +
b1000 "
b1000 )
b11 !
b11 *
b10 #
b10 (
b0 '
b11101110 $
b11101110 %
#180000
b1000 +
b111 "
b111 )
b11 !
b11 *
b10 #
b10 (
b0 '
b11101101 $
b11101101 %
#190000
b1000 +
b110 "
b110 )
b11 !
b11 *
b10 #
b10 (
b0 '
b11101100 $
b11101100 %
