數位系統實習/LAB5/LAB5_2/LAB5_2.v
module LAB5_2 (clk,fout,rst);
input clk,rst;
output reg fout;
reg [3:0] out;

initial begin
    out=4'b1010;
end

always @(posedge clk or negedge rst) begin
    if (rst==0)begin
        fout=1'b0;
    end else if (out==1) begin
        fout<=~fout;
        out=4'b1010;
    end
     else out<=out-1;
end

endmodule //LAB5_2

數位系統實習/LAB5/LAB5_2/t_LAB5_2.v
`include "LAB5_2.v"
`timescale 1ps/1ps
module t_LAB5_2 ();

reg clk;
reg rst;
// wires                                               
wire fout;

// assign statements (if any)                          
LAB5_2 i1 (
// port map - connection between master ports and signals/registers   
	.clk(clk),
	.fout(fout),
	.rst(rst)
);
initial 
begin 
#1000000 $stop;
end 

// clk
always
begin
	clk = 1'b0;
	clk = #10000 1'b1;
	#10000;
end 

// rst
initial
begin
	rst = 1'b0;
	rst = #20000 1'b1;
end 


initial begin
    $dumpfile("LAB5_2.vcd");
    $dumpvars(0, t_LAB5_2);
end
endmodule //t_LAB5_2

數位系統實習/LAB5/LAB5_2/build/LAB5_2.vcd
$date
	Thu Oct  2 03:43:48 2025
$end
$version
	Icarus Verilog
$end
$timescale
	1ps
$end
$scope module t_LAB5_2 $end
$var wire 1 ! fout $end
$var reg 1 " clk $end
$var reg 1 # rst $end
$scope module i1 $end
$var wire 1 " clk $end
$var wire 1 # rst $end
$var reg 1 ! fout $end
$var reg 4 $ out [3:0] $end
$upscope $end
$upscope $end
$enddefinitions $end
$comment Show the parameter values. $end
$dumpall
$end
#0
$dumpvars
b1010 $
0#
0"
0!
$end
#10000
1"
#20000
0"
1#
#30000
b1001 $
1"
#40000
0"
#50000
b1000 $
1"
#60000
0"
#70000
b111 $
1"
#80000
0"
#90000
b110 $
1"
#100000
0"
#110000
b101 $
1"
#120000
0"
#130000
b100 $
1"
#140000
0"
#150000
b11 $
1"
#160000
0"
#170000
b10 $
1"
#180000
0"
#190000
b1 $
1"
#200000
0"
#210000
1!
b1010 $
1"
#220000
0"
#230000
b1001 $
1"
#240000
0"
#250000
b1000 $
1"
#260000
0"
#270000
b111 $
1"
#280000
0"
#290000
b110 $
1"
#300000
0"
#310000
b101 $
1"
#320000
0"
#330000
b100 $
1"
#340000
0"
#350000
b11 $
1"
#360000
0"
#370000
b10 $
1"
#380000
0"
#390000
b1 $
1"
#400000
0"
#410000
0!
b1010 $
1"
#420000
0"
#430000
b1001 $
1"
#440000
0"
#450000
b1000 $
1"
#460000
0"
#470000
b111 $
1"
#480000
0"
#490000
b110 $
1"
#500000
0"
#510000
b101 $
1"
#520000
0"
#530000
b100 $
1"
#540000
0"
#550000
b11 $
1"
#560000
0"
#570000
b10 $
1"
#580000
0"
#590000
b1 $
1"
#600000
0"
#610000
1!
b1010 $
1"
#620000
0"
#630000
b1001 $
1"
#640000
0"
#650000
b1000 $
1"
#660000
0"
#670000
b111 $
1"
#680000
0"
#690000
b110 $
1"
#700000
0"
#710000
b101 $
1"
#720000
0"
#730000
b100 $
1"
#740000
0"
#750000
b11 $
1"
#760000
0"
#770000
b10 $
1"
#780000
0"
#790000
b1 $
1"
#800000
0"
#810000
0!
b1010 $
1"
#820000
0"
#830000
b1001 $
1"
#840000
0"
#850000
b1000 $
1"
#860000
0"
#870000
b111 $
1"
#880000
0"
#890000
b110 $
1"
#900000
0"
#910000
b101 $
1"
#920000
0"
#930000
b100 $
1"
#940000
0"
#950000
b11 $
1"
#960000
0"
#970000
b10 $
1"
#980000
0"
#990000
b1 $
1"
