數位系統實習/Lab2/LAB2_2/LAB2_2.v
//乘法器製作
module half_adder (X,Y,S,C);
    input X,Y;
    output S,C;

    assign S=X^Y;      
    assign C= X&Y;   
endmodule

module LAB2_2 (A,B,C);
    input [1:0]A,B;
    output [3:0]C;
    wire w1,w2,w_carry;

    assign C[0] = A[0] & B[0];
    assign w1 = A[0] & B[1];
    assign w2 = A[1] & B[0];
    assign w3 = A[1] & B[1];
    half_adder M1(.X(w1), .Y(w2), .S(C[1]), .C(w_carry));
    half_adder M2(.X(w3), .Y(w_carry), .S(C[2]), .C(C[3]));
endmodule //LAB2_2

數位系統實習/Lab2/LAB2_2/t_LAB2_2.v
`include "LAB2_2.v"
`timescale 1ps/1ps

module t_LAB2_2 ;

initial begin
    $dumpfile("LAB2_2.vcd");
    $dumpvars(0, t_LAB2_2);
end

// constants                                           
// general purpose registers
reg [1:0] A;
reg [1:0] B;
// wires                                               
wire [3:0] C;

// assign statements (if any)                          
LAB2_2 i1 (
// port map - connection between master ports and signals/registers   
	.A(A),
	.B(B),
	.C(C)
);
initial 
begin 
#300000 $finish;
end 
// A[ 1 ]
initial
begin
	A[1] = 1'b0;
	A[1] = #30000 1'b1;
	A[1] = #30000 1'b0;
	A[1] = #30000 1'b1;
	A[1] = #30000 1'b0;
	A[1] = #30000 1'b1;
	A[1] = #30000 1'b0;
	A[1] = #30000 1'b1;
	A[1] = #30000 1'b0;
end 
// A[ 0 ]
initial
begin
	repeat(2)
	begin
		A[0] = 1'b0;
		A[0] = #15000 1'b1;
		# 15000;
	end
	repeat(2)
	begin
		A[0] = 1'b0;
		A[0] = #15000 1'b1;
		# 15000;
	end
	repeat(2)
	begin
		A[0] = 1'b0;
		A[0] = #15000 1'b1;
		# 15000;
	end
	repeat(2)
	begin
		A[0] = 1'b0;
		A[0] = #15000 1'b1;
		# 15000;
	end
	A[0] = 1'b0;
end 
// B[ 1 ]
initial
begin
	B[1] = 1'b0;
	B[1] = #40000 1'b1;
	B[1] = #40000 1'b0;
	B[1] = #40000 1'b1;
	B[1] = #40000 1'b0;
	B[1] = #40000 1'b1;
	B[1] = #40000 1'b0;
end 
// B[ 0 ]
initial
begin
	repeat(2)
	begin
		B[0] = 1'b0;
		B[0] = #20000 1'b1;
		# 20000;
	end
	repeat(2)
	begin
		B[0] = 1'b0;
		B[0] = #20000 1'b1;
		# 20000;
	end
	repeat(2)
	begin
		B[0] = 1'b0;
		B[0] = #20000 1'b1;
		# 20000;
	end
	B[0] = 1'b0;
end 

endmodule //t_LAB2_2

數位系統實習/Lab2/LAB2_2/build/LAB2_2.vcd
$date
	Thu Sep 11 00:42:53 2025
$end
$version
	Icarus Verilog
$end
$timescale
	1ps
$end
$scope module t_LAB2_2 $end
$var wire 4 ! C [3:0] $end
$var reg 2 " A [1:0] $end
$var reg 2 # B [1:0] $end
$scope module i1 $end
$var wire 2 $ A [1:0] $end
$var wire 2 % B [1:0] $end
$var wire 1 & w1 $end
$var wire 1 ' w2 $end
$var wire 1 ( w3 $end
$var wire 1 ) w_carry $end
$var wire 4 * C [3:0] $end
$scope module M1 $end
$var wire 1 ) C $end
$var wire 1 + S $end
$var wire 1 & X $end
$var wire 1 ' Y $end
$upscope $end
$scope module M2 $end
$var wire 1 , C $end
$var wire 1 - S $end
$var wire 1 ( X $end
$var wire 1 ) Y $end
$upscope $end
$upscope $end
$upscope $end
$enddefinitions $end
$comment Show the parameter values. $end
$dumpall
$end
#0
$dumpvars
0-
0,
0+
b0 *
0)
0(
0'
0&
b0 %
b0 $
b0 #
b0 "
b0 !
$end
#15000
b1 "
b1 $
#20000
b1 !
b1 *
b1 #
b1 %
#30000
1+
b10 !
b10 *
1'
b10 "
b10 $
#40000
0+
b100 !
b100 *
1-
0'
1(
b10 #
b10 %
#45000
b110 !
b110 *
1+
1&
b11 "
b11 $
#60000
0+
b0 !
b0 *
0-
0&
0(
b11 #
b11 %
b0 "
b0 $
#75000
1+
b11 !
b11 *
1&
b1 "
b1 $
#80000
0+
b0 !
b0 *
0&
b0 #
b0 %
#90000
b10 "
b10 $
#100000
b10 !
b10 *
1+
1'
b1 #
b1 %
#105000
b11 !
b11 *
b11 "
b11 $
#120000
0+
b0 !
b0 *
0'
b0 "
b0 $
b10 #
b10 %
#135000
b10 !
b10 *
1+
1&
b1 "
b1 $
#140000
b11 !
b11 *
b11 #
b11 %
#150000
1-
b110 !
b110 *
0&
1'
1(
b10 "
b10 $
#160000
0+
b0 !
b0 *
0-
0'
0(
b0 #
b0 %
#165000
b11 "
b11 $
#180000
b1 #
b1 %
b0 "
b0 $
#195000
b1 !
b1 *
b1 "
b1 $
#200000
1+
b10 !
b10 *
1&
b10 #
b10 %
#210000
0+
b100 !
b100 *
1-
0&
1(
b10 "
b10 $
#220000
b110 !
b110 *
1+
1'
b11 #
b11 %
#225000
0-
1,
0+
1)
b1001 !
b1001 *
1&
b11 "
b11 $
#240000
0)
0-
0,
b0 !
b0 *
0'
0&
0(
b0 "
b0 $
b0 #
b0 %
