數位邏輯/full_adder/full_adder.v
module Prob_6_54 (output reg [3:0] SR_A, input Shift_control, SI, CLK, Clear_b);
  reg [3:0] SR_B;
  wire S;
  wire Q;
  wire SI_A = S;
  wire SO_A = SR_A[0];
  wire SO_B = SR_B[0];
  wire SI_B = SI;
  and (J_in, SO_A, SO_B);
  nor (K_in, SO_A, SO_B);
  xor (S, SO_A, SO_B, Q);
  //
  always @ (posedge CLK)
    if (Clear_b == 1'b0) SR_A<= 4'b0; 
else if (Shift_control) SR_A <= {SI_A, SR_A[3:1]};
  always @ (posedge CLK)
    if (Clear_b == 1'b0) SR_B <= 4'b0; 
else if (Shift_control) SR_B <= {SI_B, SR_B[3:1]};
  // gated clock
  and (clk_to_JKFF, CLK, Shift_control);		
  JKFF M1 (Q, J_in, K_in, clk_to_JKFF, Clear_b);
endmodule

// module FA (output S, C, input x, y, z);
//   assign {C, S} = x + y + z;
// endmodule
module JKFF (output reg Q, input J_in, K_in, C, Clear_b);
  always @ (posedge C) if (Clear_b == 1'b0) Q <= 1'b0; else
    case ({J_in, K_in})
      2'b00:		Q <= Q;
      2'b01:		Q <= 1'b0;
      2'b10:		Q <= 1'b1;
      2'b11:		Q <= !Q;
    endcase
endmodule

module t_Prob_6_54 ();
  wire [3:0] SR_A;
  reg Shift_control, SI, CLK, Clear_b;
  //
  Prob_6_54 M0 (SR_A, Shift_control, SI, CLK, Clear_b);
  initial #400 $finish;			// sequence of 3s
  initial begin CLK = 0; forever #5 CLK = ~CLK; end
  initial fork
     Clear_b = 0;			
    #20 Clear_b = 1;		
    #40 Shift_control = 0;
    #145 Shift_control = 1;
    #225 Shift_control = 0;
    SI = 0;   // Serial input to SRB
    #100 SI = 1;
    // #120 SI = 0;
    // #140 SI = 1;
    // #160 SI = 0;
    // #180 SI = 1;
    // #200 SI = 0;
    $dumpfile("dump.vcd");
    $dumpvars(0,t_Prob_6_54);
  join
endmodule

數位邏輯/full_adder/dump.vcd
$date
	Tue Jan 24 22:58:03 2023
$end
$version
	Icarus Verilog
$end
$timescale
	1s
$end
$scope module t_Prob_6_54 $end
$var wire 4 ! SR_A [3:0] $end
$var reg 1 " CLK $end
$var reg 1 # Clear_b $end
$var reg 1 $ SI $end
$var reg 1 % Shift_control $end
$scope module M0 $end
$var wire 1 " CLK $end
$var wire 1 # Clear_b $end
$var wire 1 & J_in $end
$var wire 1 ' K_in $end
$var wire 1 ( S $end
$var wire 1 $ SI $end
$var wire 1 ) SI_A $end
$var wire 1 * SI_B $end
$var wire 1 % Shift_control $end
$var wire 1 + clk_to_JKFF $end
$var wire 1 , SO_B $end
$var wire 1 - SO_A $end
$var wire 1 . Q $end
$var reg 4 / SR_A [3:0] $end
$var reg 4 0 SR_B [3:0] $end
$scope module M1 $end
$var wire 1 + C $end
$var wire 1 # Clear_b $end
$var wire 1 & J_in $end
$var wire 1 ' K_in $end
$var reg 1 . Q $end
$upscope $end
$upscope $end
$upscope $end
$enddefinitions $end
$comment Show the parameter values. $end
$dumpall
$end
#0
$dumpvars
bx 0
bx /
x.
x-
x,
0+
0*
x)
x(
x'
x&
x%
0$
0#
0"
bx !
$end
#5
1'
0&
0)
0(
0-
0,
0.
b0 !
b0 /
b0 0
x+
1"
#10
0+
0"
#15
x+
1"
#20
0+
0"
1#
#25
x+
1"
#30
0+
0"
#35
x+
1"
#40
0+
0"
0%
#45
1"
#50
0"
#55
1"
#60
0"
#65
1"
#70
0"
#75
1"
#80
0"
#85
1"
#90
0"
#95
1"
#100
0"
1*
1$
#105
1"
#110
0"
#115
1"
#120
0"
#125
1"
#130
0"
#135
1"
#140
0"
#145
b1000 0
1+
1"
1%
#150
0+
0"
#155
b1100 0
1+
1"
#160
0+
0"
#165
b1110 0
1+
1"
#170
0+
0"
#175
1)
1(
0'
1,
b1111 0
1+
1"
#180
0+
0"
#185
b1000 !
b1000 /
1+
1"
#190
0+
0"
#195
b1100 !
b1100 /
1+
1"
#200
0+
0"
#205
b1110 !
b1110 /
1+
1"
#210
0+
0"
#215
0)
0(
1&
1-
b1111 !
b1111 /
1+
1"
#220
0+
0"
#225
1"
0%
