數位系統實習/LAB5/LAB5_1/LAB5_1.v
module LAB5_1 (clear,clk,count,in,load,out);
input clear,clk,load,count;
input [3:0] in;
output reg [3:0] out;

always @(posedge clk or posedge clear)
begin
   if(clear==1'b1)
       out <= 4'b0000;
   else if(load==1'b1)
       out = in;
   else if(count==1'b1)
       out <= out+4'b0001;
	else
		 out<=out;
end

endmodule //LAB5_1

數位系統實習/LAB5/LAB5_1/t_LAB5_1.v
`include "LAB5_1.v"
`timescale 1ps/1ps
module t_LAB5_1 ();

// constants                                           
// general purpose registers
reg clear;
reg clk;
reg count;
reg [3:0] in;
reg load;
// wires                                               
wire [3:0] out;

// assign statements (if any)                          
LAB5_1 i1 (
// port map - connection between master ports and signals/registers   
	.clear(clear),
	.clk(clk),
	.count(count),
	.in(in),
	.load(load),
	.out(out)
);
initial 
begin 
#500000 $stop;
end 

// clear
initial
begin
	clear = 1'b1;
	clear = #40000 1'b0;
end 

// clk
always
begin
	clk = 1'b0;
	clk = #10000 1'b1;
	#10000;
end 

// count
initial
begin
	count = 1'b0;
	count = #70000 1'b1;
	count = #170000 1'b0;

    count = #40000 1'b1;
    count = #20000 1'b0;
end 

// load
initial
begin
	load = 1'b0;
	load = #40000 1'b1;
	load = #20000 1'b0;
end 
// in[ 3 ]
initial
begin
	in[3] = 1'b0;
	in[3] = #40000 1'b1;
	in[3] = #20000 1'b0;
end 
// in[ 2 ]
initial
begin
	in[2] = 1'b0;
	in[2] = #40000 1'b1;
	in[2] = #20000 1'b0;
end 
// in[ 1 ]
initial
begin
	in[1] = 1'b0;
end 
// in[ 0 ]
initial
begin
	in[0] = 1'b0;
end 

initial begin
    $dumpfile("t_LAB5_1.vcd");
    $dumpvars(0,t_LAB5_1);
end
endmodule //t_LAB5_1

數位系統實習/LAB5/LAB5_1/build/t_LAB5_1.vcd
$date
	Thu Oct  2 01:42:12 2025
$end
$version
	Icarus Verilog
$end
$timescale
	1ps
$end
$scope module t_LAB5_1 $end
$var wire 4 ! out [3:0] $end
$var reg 1 " clear $end
$var reg 1 # clk $end
$var reg 1 $ count $end
$var reg 4 % in [3:0] $end
$var reg 1 & load $end
$scope module i1 $end
$var wire 1 " clear $end
$var wire 1 # clk $end
$var wire 1 $ count $end
$var wire 4 ' in [3:0] $end
$var wire 1 & load $end
$var reg 4 ( out [3:0] $end
$upscope $end
$upscope $end
$enddefinitions $end
$comment Show the parameter values. $end
$dumpall
$end
#0
$dumpvars
b0 (
b0 '
0&
b0 %
0$
0#
1"
b0 !
$end
#10000
1#
#20000
0#
#30000
1#
#40000
0#
b1100 %
b1100 '
1&
0"
#50000
b1100 !
b1100 (
1#
#60000
0#
b0 %
b0 '
0&
#70000
b1101 !
b1101 (
1#
1$
#80000
0#
#90000
b1110 !
b1110 (
1#
#100000
0#
#110000
b1111 !
b1111 (
1#
#120000
0#
#130000
b0 !
b0 (
1#
#140000
0#
#150000
b1 !
b1 (
1#
#160000
0#
#170000
b10 !
b10 (
1#
#180000
0#
#190000
b11 !
b11 (
1#
#200000
0#
#210000
b100 !
b100 (
1#
#220000
0#
#230000
b101 !
b101 (
1#
#240000
0#
0$
#250000
1#
#260000
0#
#270000
1#
#280000
0#
1$
#290000
b110 !
b110 (
1#
#300000
0#
0$
