數位系統實習/LAB7/LAB7_1/LAB7_1.v
module LAB7_1 #(
    parameter s0 = 2'b00,
              s1 = 2'b01,
              s2 = 2'b10,
              s3 = 2'b11
)(
    input clk,
    input in,
    input rst,
    output reg out,
    output reg [1:0] out_state
);

    reg [1:0] state, next_state;

    always @(state,in) begin
        case (state)
            s0: next_state = in ? s1 : s0;
            s1: next_state = in ? s3 : s0;
            s2: next_state = in ? s2 : s0;
            s3: next_state = in ? s2 : s0;
            default: next_state = s0;
        endcase
    end

    always @(posedge clk or negedge rst) begin
        if (!rst) begin
            state <= s0;
            out <= 0;
        end else begin
            state <= next_state;
            case (next_state)
                s0: out <= (state == s1 || state == s2 || state == s3);
                default: out <= 0;
            endcase
        end
        out_state <= next_state;
    end

endmodule

數位系統實習/LAB7/LAB7_1/t_LAB7_1.v
`include "數位系統實習/LAB7/LAB7_1/LAB7_1.v"
`timescale 1ps/1ps

module t_LAB7_1;
reg clk;
reg in;
reg rst;
// wires                                               
wire out;
wire [1:0] out_state;

// assign statements (if any)                          
LAB7_1 i1 (
// port map - connection between master ports and signals/registers   
	.clk(clk),
	.in(in),
	.out(out),
	.out_state(out_state),
	.rst(rst)
);
initial 
begin 
#100000 $stop;
end 

// clk
always
begin
	clk = 1'b0;
	clk = #5000 1'b1;
	#5000;
end 

// in
initial
begin
	in = 1'b1;
	in = #40000 1'b0;
	in = #10000 1'b1;
end 

// rst
initial
begin
	rst = 1'b0;
	rst = #10000 1'b1;
end 
initial begin
    $dumpfile("t_LAB7_1.vcd");
    $dumpvars(0, t_LAB7_1);
end
endmodule

數位系統實習/LAB7/LAB7_1/t_LAB7_1.vcd
$date
	Thu Oct 16 01:38:17 2025
$end
$version
	Icarus Verilog
$end
$timescale
	1ps
$end
$scope module t_LAB7_1 $end
$var wire 2 ! out_state [1:0] $end
$var wire 1 " out $end
$var reg 1 # clk $end
$var reg 1 $ in $end
$var reg 1 % rst $end
$scope module i1 $end
$var wire 1 # clk $end
$var wire 1 $ in $end
$var wire 1 % rst $end
$var parameter 2 & s0 $end
$var parameter 2 ' s1 $end
$var parameter 2 ( s2 $end
$var parameter 2 ) s3 $end
$var reg 2 * next_state [1:0] $end
$var reg 1 " out $end
$var reg 2 + out_state [1:0] $end
$var reg 2 , state [1:0] $end
$upscope $end
$upscope $end
$enddefinitions $end
$comment Show the parameter values. $end
$dumpall
b11 )
b10 (
b1 '
b0 &
$end
#0
$dumpvars
b0 ,
b0 +
b1 *
0%
1$
0#
0"
b0 !
$end
#5000
b1 !
b1 +
1#
#10000
0#
1%
#15000
b11 *
b1 ,
1#
#20000
0#
#25000
b10 *
b11 !
b11 +
b11 ,
1#
#30000
0#
#35000
b10 !
b10 +
b10 ,
1#
#40000
b0 *
0#
0$
#45000
b0 !
b0 +
1"
b0 ,
1#
#50000
b1 *
0#
1$
#55000
b11 *
b1 !
b1 +
0"
b1 ,
1#
#60000
0#
#65000
b10 *
b11 !
b11 +
b11 ,
1#
#70000
0#
#75000
b10 !
b10 +
b10 ,
1#
