數位系統實習/Lab2/Full_adder/full_adder.v
module full_adder (
    A,B,C0,C1,S
);
    input A,B,C0;
    output C1,S;

    assign S=A^B^C0;
    assign C1=(A&B)|(B&C0)|(C0&A);
endmodule //full_adder

數位系統實習/Lab2/Full_adder/testbench_full_adder.v
`include "full_adder.v"
`timescale 1ns/1ps

module testbench_full_adder;

reg a, b, cin;
wire sum, cout;

// Instantiate the full adder module
full_adder uut (
    .A(a),
    .B(b),
    .C0(cin),
    .S(sum),
    .C1(cout)
);


initial begin
    $display("a b cin | sum cout");
    $display("---------------");
    // Test all input combinations
    a = 0; b = 0; cin = 0; #10;
    $display("%b %b  %b  |  %b   %b", a, b, cin, sum, cout);

    a = 0; b = 0; cin = 1; #10;
    $display("%b %b  %b  |  %b   %b", a, b, cin, sum, cout);

    a = 0; b = 1; cin = 0; #10;
    $display("%b %b  %b  |  %b   %b", a, b, cin, sum, cout);

    a = 0; b = 1; cin = 1; #10;
    $display("%b %b  %b  |  %b   %b", a, b, cin, sum, cout);

    a = 1; b = 0; cin = 0; #10;
    $display("%b %b  %b  |  %b   %b", a, b, cin, sum, cout);

    a = 1; b = 0; cin = 1; #10;
    $display("%b %b  %b  |  %b   %b", a, b, cin, sum, cout);

    a = 1; b = 1; cin = 0; #10;
    $display("%b %b  %b  |  %b   %b", a, b, cin, sum, cout);

    a = 1; b = 1; cin = 1; #10;
    $display("%b %b  %b  |  %b   %b", a, b, cin, sum, cout);

    $finish;
end

initial begin
    $dumpfile("testbench_full_adder.vcd");
    $dumpvars(0, testbench_full_adder);
end

endmodule

數位系統實習/Lab2/Full_adder/build/testbench_full_adder.vcd
$date
	Wed Sep 10 23:41:07 2025
$end
$version
	Icarus Verilog
$end
$timescale
	1ps
$end
$scope module testbench_full_adder $end
$var wire 1 ! sum $end
$var wire 1 " cout $end
$var reg 1 # a $end
$var reg 1 $ b $end
$var reg 1 % cin $end
$scope module uut $end
$var wire 1 # A $end
$var wire 1 $ B $end
$var wire 1 % C0 $end
$var wire 1 " C1 $end
$var wire 1 ! S $end
$upscope $end
$upscope $end
$enddefinitions $end
$comment Show the parameter values. $end
$dumpall
$end
#0
$dumpvars
0%
0$
0#
0"
0!
$end
#10000
1!
1%
#20000
0%
1$
#30000
1"
0!
1%
#40000
0"
1!
0%
0$
1#
#50000
1"
0!
1%
#60000
0%
1$
#70000
1!
1%
