數位邏輯/Project/project_final.v
module project(input CONV,input [9:0]Vpeak,output reset_signal);
    LMM311DR M1(.Vpeak(Vpeak),.LM311DR_signal(LM311DR_signal));
    wire LM311DR_signal;
    wire dff_clear,Dff_output;
    wire LM311DR_not;
    assign LM311DR_not = ~LM311DR_signal; // 反轉 LM311DR_signal
    and(reset_signal, LM311DR_not, Dff_output);
    nand(dff_clear,Dff_output,LM311DR_signal);
    Dff M0(.D(1'b1),.clk(CONV),.clear(dff_clear),.set(1'b1),.Q(Dff_output));
endmodule

module Dff(input D,clk,clear,set,output reg Q); //D flip-flop
    always@(posedge clk or negedge clear or negedge set)begin
    if (clear==1'b0 && set==1'b0)
        Q<=1'b1;
    else if  (set==1'b0)
        Q<=1'b1; //保持
    else if (clear==1'b0)
        Q<=1'b0; //清除
    else
        Q<=D; //維持原狀
    end
endmodule

module LMM311DR(input [9:0]Vpeak,output reg LM311DR_signal); //LM311DR(模塊)
    parameter Vref = 10'b0110001000; // 392 in decimal(差不多383mV)
    always@(*)begin
        if(Vpeak>Vref)
            LM311DR_signal=1'b0;
        else
            LM311DR_signal=1'b1;
    end
endmodule

//testbench
`timescale 1us/1ns //設定時間單位為微秒 (us)
module testbench();
    reg CONV;
    reg [9:0]Vpeak;//input
    wire reset_signal;//output
    project M2(CONV,Vpeak,reset_signal);
    initial #150 $finish; //模擬150us時間
    parameter HIGH_TIME = 1.39;   // 高電平時間 (us)
    parameter LOW_TIME  = 26.39; // 低電平時間 (us)
    // 36kHz clk
    initial begin 
        CONV=1'b0;//函數產生器CH2未開啟
        #40CONV=1'b1;//40us函數產生器CH2開啟
        forever begin
            #HIGH_TIME CONV=~CONV;
            #LOW_TIME CONV=~CONV;
        end
    end
    always @(reset_signal) begin
        if (reset_signal == 1'b1)
            #0.3Vpeak = 10'b0000000000; // 0V
    end
    initial fork
        #0Vpeak=10'b0000000000;
        #40Vpeak=10'b0010001000;
        #80Vpeak=10'b1110001100;
        #120Vpeak=10'b1010001000;
        $dumpfile("testbench.vcd");
        $dumpvars(0,testbench); //產生波形檔
    join   
endmodule

數位邏輯/Project/build/dump.vcd
$date
	Thu Feb 27 12:38:07 2025
$end
$version
	Icarus Verilog
$end
$timescale
	1ns
$end
$scope module testbench $end
$var wire 1 ! reset_signal $end
$var real 1 " HIGH_TIME $end
$var real 1 # LOW_TIME $end
$var reg 1 $ CONV $end
$var reg 10 % Vpeak [9:0] $end
$scope module M2 $end
$var wire 1 $ CONV $end
$var wire 1 & LM311DR_not $end
$var wire 10 ' Vpeak [9:0] $end
$var wire 1 ( dff_clear $end
$var wire 1 ! reset_signal $end
$var wire 1 ) LM311DR_signal $end
$var wire 1 * Dff_output $end
$scope module M0 $end
$var wire 1 + D $end
$var wire 1 ( clear $end
$var wire 1 $ clk $end
$var wire 1 , set $end
$var reg 1 * Q $end
$upscope $end
$scope module M1 $end
$var wire 10 - Vpeak [9:0] $end
$var parameter 10 . Vref $end
$var reg 1 ) LM311DR_signal $end
$upscope $end
$upscope $end
$upscope $end
$enddefinitions $end
$comment Show the parameter values. $end
$dumpall
b110001000 .
r26.39 #
r1.39 "
$end
#0
$dumpvars
b0 -
1,
1+
x*
1)
x(
b0 '
0&
b0 %
0$
0!
$end
#40000
1(
0*
b10001000 %
b10001000 '
b10001000 -
1$
#41390
0$
#67780
1(
0*
1$
#69170
0$
#80000
1&
0)
b1110001100 %
b1110001100 '
b1110001100 -
#95560
1!
1*
1$
#95860
0*
0!
1(
0&
1)
b0 %
b0 '
b0 -
#96950
0$
#120000
1&
0)
b1010001000 %
b1010001000 '
b1010001000 -
#123340
1!
1*
1$
#123640
0*
0!
1(
0&
1)
b0 %
b0 '
b0 -
