數位系統實習/LAB4/LAB4_1.v
//4 bit CLA
module LAB4_1 (input [3:0] A,input [3:0] B,input C0,output [3:0] S,output C4 );
    reg [3:0] P;
    reg [3:0] G;
    integer i;
    wire C1,C2,C3;

    always @(*) begin
        for (i=0;i<4;i=i+1) begin
            P[i] = A[i] ^ B[i];
            G[i] = A[i] & B[i];
        end
    end//HA4顆

    assign S[0] = P[0] ^ C0;
    assign S[1] = P[1] ^ C1;
    assign S[2] = P[2] ^ C2;
    assign S[3] = P[3] ^ C3;

    assign C1= P[0]&C0 | G[0];
    assign C2= P[1]&C1 | G[1] | P[1]&P[0]&C0;
    assign C3= P[2]&C2 | G[2] | P[2]&P[1]&G[0] | P[2]&P[1]&P[0]&C0;
    assign C4= G[3] | P[3]&G[2] | P[3]&P[2]&G[1] | P[3]&P[2]&P[1]&G[0] | P[3]&P[2]&P[1]&P[0]&C0; 

endmodule //LAB4_1

數位系統實習/LAB4/t_LAB4_1.v
`include "LAB4_1.v"
`timescale 1ps/1ps

module t_LAB4_1 ();
// constants                                           
// general purpose registers
reg [3:0] A;
reg [3:0] B;
reg C0;
// wires                                               
wire C4;
wire [3:0] S;

// assign statements (if any)                          
LAB4_1 i1 (
// port map - connection between master ports and signals/registers   
	.A(A),
	.B(B),
	.C0(C0),
	.C4(C4),
	.S(S)
);
initial 
begin 
#1000000 $stop;
end 
// A[ 3 ]
initial
begin
	repeat(6)
	begin
		A[3] = 1'b0;
		A[3] = #80000 1'b1;
		# 80000;
	end
	A[3] = 1'b0;
end 
// A[ 2 ]
initial
begin
	repeat(12)
	begin
		A[2] = 1'b0;
		A[2] = #40000 1'b1;
		# 40000;
	end
	A[2] = 1'b0;
end 
// A[ 1 ]
always
begin
	A[1] = 1'b0;
	A[1] = #20000 1'b1;
	#20000;
end 
// A[ 0 ]
always
begin
	A[0] = 1'b0;
	A[0] = #10000 1'b1;
	#10000;
end 
// B[ 3 ]
initial
begin
	B[3] = 1'b0;
	# 50000;
	repeat(5)
	begin
		B[3] = 1'b1;
		B[3] = #80000 1'b0;
		# 80000;
	end
	B[3] = 1'b1;
	B[3] = #80000 1'b0;
end 
// B[ 2 ]
initial
begin
	B[2] = 1'b0;
	# 10000;
	repeat(12)
	begin
		B[2] = 1'b1;
		B[2] = #40000 1'b0;
		# 40000;
	end
	B[2] = 1'b1;
end 
// B[ 1 ]
initial
begin
	B[1] = 1'b1;
	# 10000;
	repeat(24)
	begin
		B[1] = 1'b0;
		B[1] = #20000 1'b1;
		# 20000;
	end
	B[1] = 1'b0;
	B[1] = #20000 1'b1;
end 
// B[ 0 ]
always
begin
	B[0] = 1'b1;
	B[0] = #10000 1'b0;
	#10000;
end 

// C0
initial
begin
	C0 = 1'b0;
	C0 = #60000 1'b1;
	C0 = #50000 1'b0;
end 

initial begin
    $dumpfile("t_LAB4_1.vcd");
    $dumpvars(0,t_LAB4_1);
end
endmodule //t_LAB4_1

數位系統實習/LAB4/LAB4_1.vcd
$date
	Thu Sep 25 13:00:06 2025
$end
$version
	Icarus Verilog
$end
$timescale
	1ps
$end
$scope module t_LAB4_1 $end
$var wire 4 ! S [3:0] $end
$var wire 1 " C4 $end
$var reg 4 # A [3:0] $end
$var reg 4 $ B [3:0] $end
$var reg 1 % C0 $end
$scope module i1 $end
$var wire 4 & A [3:0] $end
$var wire 4 ' B [3:0] $end
$var wire 1 % C0 $end
$var wire 1 ( C1 $end
$var wire 1 ) C2 $end
$var wire 1 * C3 $end
$var wire 1 " C4 $end
$var wire 4 + S [3:0] $end
$var reg 4 , G [3:0] $end
$var reg 4 - P [3:0] $end
$var integer 32 . i [31:0] $end
$upscope $end
$upscope $end
$enddefinitions $end
$comment Show the parameter values. $end
$dumpall
$end
#0
$dumpvars
b100 .
b11 -
b0 ,
b11 +
0*
0)
0(
b11 '
b0 &
0%
b11 $
b0 #
0"
b11 !
$end
#10000
b101 !
b101 +
b101 -
b100 .
b100 $
b100 '
b1 #
b1 &
#20000
b111 !
b111 +
b111 -
b100 .
b101 $
b101 '
b10 #
b10 &
#30000
1*
1)
b1001 !
b1001 +
b10 ,
b101 -
b100 .
b11 #
b11 &
b110 $
b110 '
#40000
0)
b1011 !
b1011 +
b100 ,
b11 -
b100 .
b111 $
b111 '
b100 #
b100 &
#50000
0*
b1101 !
b1101 +
b0 ,
b1101 -
b100 .
b101 #
b101 &
b1000 $
b1000 '
#60000
1*
1"
1)
1(
b1111 -
b100 .
b0 !
b0 +
b1001 $
b1001 '
b110 #
b110 &
1%
#70000
b10 !
b10 +
b10 ,
b1101 -
b100 .
b111 #
b111 &
b1010 $
b1010 '
#80000
0*
b100 !
b100 +
b1000 ,
b11 -
b100 .
b1011 $
b1011 '
b1000 #
b1000 &
#90000
0*
0)
b110 !
b110 +
b101 -
b100 .
b1001 #
b1001 &
b1100 $
b1100 '
#100000
1*
1)
b1000 !
b1000 +
b111 -
b100 .
b1101 $
b1101 '
b1010 #
b1010 &
#110000
0(
b1010 ,
b101 -
b100 .
b1001 !
b1001 +
b1011 #
b1011 &
b1110 $
b1110 '
0%
#120000
0)
b1011 !
b1011 +
b1100 ,
b11 -
b100 .
b1111 $
b1111 '
b1100 #
b1100 &
#130000
0"
0*
b1101 !
b1101 +
b0 ,
b1101 -
b100 .
b1101 #
b1101 &
b0 $
b0 '
#140000
b1111 !
b1111 +
b1111 -
b100 .
b1 $
b1 '
b1110 #
b1110 &
#150000
1*
1"
1)
b1 !
b1 +
b10 ,
b1101 -
b100 .
b1111 #
b1111 &
b10 $
b10 '
#160000
0*
0"
0)
b11 !
b11 +
b0 ,
b11 -
b100 .
b11 $
b11 '
b0 #
b0 &
#170000
b101 !
b101 +
b101 -
b100 .
b1 #
b1 &
b100 $
b100 '
#180000
b111 !
b111 +
b111 -
b100 .
b101 $
b101 '
b10 #
b10 &
#190000
1*
1)
b1001 !
b1001 +
b10 ,
b101 -
b100 .
b11 #
b11 &
b110 $
b110 '
#200000
0)
b1011 !
b1011 +
b100 ,
b11 -
b100 .
b111 $
b111 '
b100 #
b100 &
#210000
0*
b1101 !
b1101 +
b0 ,
b1101 -
b100 .
b101 #
b101 &
b1000 $
b1000 '
#220000
b1111 !
b1111 +
b1111 -
b100 .
b1001 $
b1001 '
b110 #
b110 &
#230000
1*
1"
1)
b1 !
b1 +
b10 ,
b1101 -
b100 .
b111 #
b111 &
b1010 $
b1010 '
#240000
0*
0)
b11 !
b11 +
b1000 ,
b11 -
b100 .
b1011 $
b1011 '
b1000 #
b1000 &
#250000
b101 !
b101 +
b101 -
b100 .
b1001 #
b1001 &
b1100 $
b1100 '
#260000
b111 !
b111 +
b111 -
b100 .
b1101 $
b1101 '
b1010 #
b1010 &
#270000
1*
1)
b1001 !
b1001 +
b1010 ,
b101 -
b100 .
b1011 #
b1011 &
b1110 $
b1110 '
#280000
0)
b1011 !
b1011 +
b1100 ,
b11 -
b100 .
b1111 $
b1111 '
b1100 #
b1100 &
#290000
0"
0*
b1101 !
b1101 +
b0 ,
b1101 -
b100 .
b1101 #
b1101 &
b0 $
b0 '
#300000
b1111 !
b1111 +
b1111 -
b100 .
b1 $
b1 '
b1110 #
b1110 &
#310000
1*
1"
1)
b1 !
b1 +
b10 ,
b1101 -
b100 .
b1111 #
b1111 &
b10 $
b10 '
#320000
0*
0"
0)
b11 !
b11 +
b0 ,
b11 -
b100 .
b11 $
b11 '
b0 #
b0 &
#330000
b101 !
b101 +
b101 -
b100 .
b1 #
b1 &
b100 $
b100 '
#340000
b111 !
b111 +
b111 -
b100 .
b101 $
b101 '
b10 #
b10 &
#350000
1*
1)
b1001 !
b1001 +
b10 ,
b101 -
b100 .
b11 #
b11 &
b110 $
b110 '
#360000
0)
b1011 !
b1011 +
b100 ,
b11 -
b100 .
b111 $
b111 '
b100 #
b100 &
#370000
0*
b1101 !
b1101 +
b0 ,
b1101 -
b100 .
b101 #
b101 &
b1000 $
b1000 '
#380000
b1111 !
b1111 +
b1111 -
b100 .
b1001 $
b1001 '
b110 #
b110 &
#390000
1*
1"
1)
b1 !
b1 +
b10 ,
b1101 -
b100 .
b111 #
b111 &
b1010 $
b1010 '
#400000
0*
0)
b11 !
b11 +
b1000 ,
b11 -
b100 .
b1011 $
b1011 '
b1000 #
b1000 &
#410000
b101 !
b101 +
b101 -
b100 .
b1001 #
b1001 &
b1100 $
b1100 '
#420000
b111 !
b111 +
b111 -
b100 .
b1101 $
b1101 '
b1010 #
b1010 &
#430000
1*
1)
b1001 !
b1001 +
b1010 ,
b101 -
b100 .
b1011 #
b1011 &
b1110 $
b1110 '
#440000
0)
b1011 !
b1011 +
b1100 ,
b11 -
b100 .
b1111 $
b1111 '
b1100 #
b1100 &
#450000
0"
0*
b1101 !
b1101 +
b0 ,
b1101 -
b100 .
b1101 #
b1101 &
b0 $
b0 '
#460000
b1111 !
b1111 +
b1111 -
b100 .
b1 $
b1 '
b1110 #
b1110 &
#470000
1*
1"
1)
b1 !
b1 +
b10 ,
b1101 -
b100 .
b1111 #
b1111 &
b10 $
b10 '
#480000
0*
0"
0)
b11 !
b11 +
b0 ,
b11 -
b100 .
b11 $
b11 '
b0 #
b0 &
#490000
b101 !
b101 +
b101 -
b100 .
b1 #
b1 &
b100 $
b100 '
#500000
b111 !
b111 +
b111 -
b100 .
b101 $
b101 '
b10 #
b10 &
#510000
1*
1)
b1001 !
b1001 +
b10 ,
b101 -
b100 .
b11 #
b11 &
b110 $
b110 '
#520000
0)
b1011 !
b1011 +
b100 ,
b11 -
b100 .
b111 $
b111 '
b100 #
b100 &
#530000
0*
b1101 !
b1101 +
b0 ,
b1101 -
b100 .
b101 #
b101 &
b1000 $
b1000 '
#540000
b1111 !
b1111 +
b1111 -
b100 .
b1001 $
b1001 '
b110 #
b110 &
#550000
1*
1"
1)
b1 !
b1 +
b10 ,
b1101 -
b100 .
b111 #
b111 &
b1010 $
b1010 '
#560000
0*
0)
b11 !
b11 +
b1000 ,
b11 -
b100 .
b1011 $
b1011 '
b1000 #
b1000 &
#570000
b101 !
b101 +
b101 -
b100 .
b1001 #
b1001 &
b1100 $
b1100 '
#580000
b111 !
b111 +
b111 -
b100 .
b1101 $
b1101 '
b1010 #
b1010 &
#590000
1*
1)
b1001 !
b1001 +
b1010 ,
b101 -
b100 .
b1011 #
b1011 &
b1110 $
b1110 '
#600000
0)
b1011 !
b1011 +
b1100 ,
b11 -
b100 .
b1111 $
b1111 '
b1100 #
b1100 &
#610000
0"
0*
b1101 !
b1101 +
b0 ,
b1101 -
b100 .
b1101 #
b1101 &
b0 $
b0 '
#620000
b1111 !
b1111 +
b1111 -
b100 .
b1 $
b1 '
b1110 #
b1110 &
#630000
1*
1"
1)
b1 !
b1 +
b10 ,
b1101 -
b100 .
b1111 #
b1111 &
b10 $
b10 '
#640000
0*
0"
0)
b11 !
b11 +
b0 ,
b11 -
b100 .
b11 $
b11 '
b0 #
b0 &
#650000
b101 !
b101 +
b101 -
b100 .
b1 #
b1 &
b100 $
b100 '
#660000
b111 !
b111 +
b111 -
b100 .
b101 $
b101 '
b10 #
b10 &
#670000
1*
1)
b1001 !
b1001 +
b10 ,
b101 -
b100 .
b11 #
b11 &
b110 $
b110 '
#680000
0)
b1011 !
b1011 +
b100 ,
b11 -
b100 .
b111 $
b111 '
b100 #
b100 &
#690000
0*
b1101 !
b1101 +
b0 ,
b1101 -
b100 .
b101 #
b101 &
b1000 $
b1000 '
#700000
b1111 !
b1111 +
b1111 -
b100 .
b1001 $
b1001 '
b110 #
b110 &
#710000
1*
1"
1)
b1 !
b1 +
b10 ,
b1101 -
b100 .
b111 #
b111 &
b1010 $
b1010 '
#720000
0*
0)
b11 !
b11 +
b1000 ,
b11 -
b100 .
b1011 $
b1011 '
b1000 #
b1000 &
#730000
b101 !
b101 +
b101 -
b100 .
b1001 #
b1001 &
b1100 $
b1100 '
#740000
b111 !
b111 +
b111 -
b100 .
b1101 $
b1101 '
b1010 #
b1010 &
#750000
1*
1)
b1001 !
b1001 +
b1010 ,
b101 -
b100 .
b1011 #
b1011 &
b1110 $
b1110 '
#760000
0)
b1011 !
b1011 +
b1100 ,
b11 -
b100 .
b1111 $
b1111 '
b1100 #
b1100 &
#770000
0"
0*
b1101 !
b1101 +
b0 ,
b1101 -
b100 .
b1101 #
b1101 &
b0 $
b0 '
#780000
b1111 !
b1111 +
b1111 -
b100 .
b1 $
b1 '
b1110 #
b1110 &
#790000
1*
1"
1)
b1 !
b1 +
b10 ,
b1101 -
b100 .
b1111 #
b1111 &
b10 $
b10 '
#800000
0*
0"
0)
b11 !
b11 +
b0 ,
b11 -
b100 .
b11 $
b11 '
b0 #
b0 &
#810000
b101 !
b101 +
b101 -
b100 .
b1 #
b1 &
b100 $
b100 '
#820000
b111 !
b111 +
b111 -
b100 .
b101 $
b101 '
b10 #
b10 &
#830000
1*
1)
b1001 !
b1001 +
b10 ,
b101 -
b100 .
b11 #
b11 &
b110 $
b110 '
#840000
0)
b1011 !
b1011 +
b100 ,
b11 -
b100 .
b111 $
b111 '
b100 #
b100 &
#850000
0*
b1101 !
b1101 +
b0 ,
b1101 -
b100 .
b101 #
b101 &
b1000 $
b1000 '
#860000
b1111 !
b1111 +
b1111 -
b100 .
b1001 $
b1001 '
b110 #
b110 &
#870000
1*
1"
1)
b1 !
b1 +
b10 ,
b1101 -
b100 .
b111 #
b111 &
b1010 $
b1010 '
#880000
0*
0)
b11 !
b11 +
b1000 ,
b11 -
b100 .
b1011 $
b1011 '
b1000 #
b1000 &
#890000
b101 !
b101 +
b101 -
b100 .
b1001 #
b1001 &
b1100 $
b1100 '
#900000
b111 !
b111 +
b111 -
b100 .
b1101 $
b1101 '
b1010 #
b1010 &
#910000
1*
1)
b1001 !
b1001 +
b1010 ,
b101 -
b100 .
b1011 #
b1011 &
b1110 $
b1110 '
#920000
0)
b1011 !
b1011 +
b1100 ,
b11 -
b100 .
b1111 $
b1111 '
b1100 #
b1100 &
#930000
0"
0*
b1101 !
b1101 +
b0 ,
b1101 -
b100 .
b1101 #
b1101 &
b0 $
b0 '
#940000
b1111 !
b1111 +
b1111 -
b100 .
b1 $
b1 '
b1110 #
b1110 &
#950000
1*
1"
1)
b1 !
b1 +
b10 ,
b1101 -
b100 .
b1111 #
b1111 &
b10 $
b10 '
#960000
0*
0"
0)
b11 !
b11 +
b0 ,
b11 -
b100 .
b11 $
b11 '
b0 #
b0 &
#970000
b101 !
b101 +
b101 -
b100 .
b1 #
b1 &
b100 $
b100 '
#980000
b111 !
b111 +
b111 -
b100 .
b101 $
b101 '
b10 #
b10 &
#990000
1*
1)
b1001 !
b1001 +
b10 ,
b101 -
b100 .
b11 #
b11 &
b110 $
b110 '
