數位系統實習/LAB4/LAB4_3.v
module LAB4_3 (D_in, clk, rst,load, D_out);
input [3:0] D_in;
input clk, rst, load;
output reg [3:0] D_out;

initial begin
    D_out = 4'b0000;
end // 設定初始值

always @(posedge clk) begin
    if (!rst) begin
        D_out <= 4'b0000;
    end
    else if (load) begin
        D_out <= D_in;
    end
    else begin
        D_out <= D_out; // Hold the value
    end
end
endmodule //LAB4_3

數位系統實習/LAB4/t_LAB4_3.v
`include "LAB4_3.v"
`timescale 1ps/1ps

module t_LAB4_3;
// constants                                           
// general purpose registers
reg [3:0] D_in;
reg clk;
reg load;
reg rst;
// wires                                               
wire [3:0] D_out;

// assign statements (if any)                          
LAB4_3 i1 (
// port map - connection between master ports and signals/registers   
	.D_in(D_in),
	.D_out(D_out),
	.clk(clk),
	.load(load),
	.rst(rst)
);
initial 
begin 
#200000 $stop;
end 
// D_in[ 3 ]
initial
begin
	D_in[3] = 1'b0;
	D_in[3] = #120000 1'b1;
	D_in[3] = #30000 1'b0;
end 
// D_in[ 2 ]
initial
begin
	D_in[2] = 1'b1;
	D_in[2] = #60000 1'b0;
	D_in[2] = #30000 1'b1;
	D_in[2] = #90000 1'b0;
end 
// D_in[ 1 ]
initial
begin
	D_in[1] = 1'b0;
	D_in[1] = #60000 1'b1;
	D_in[1] = #30000 1'b0;
	D_in[1] = #90000 1'b1;
end 
// D_in[ 0 ]
initial
begin
	D_in[0] = 1'b0;
	D_in[0] = #30000 1'b1;
	D_in[0] = #30000 1'b0;
	D_in[0] = #90000 1'b1;
	D_in[0] = #30000 1'b0;
end 

// clk
always
begin
	clk = 1'b0;
	clk = #5000 1'b1;
	#5000;
end 

// load
initial
begin
	load = 1'b1;
	load = #10000 1'b0;
	load = #30000 1'b1;
	load = #10000 1'b0;
	load = #40000 1'b1;
	load = #20000 1'b0;
end 

// rst
initial
begin
	rst = 1'b1;
	rst = #30000 1'b0;
	rst = #10000 1'b1;
end 

initial begin
    $dumpfile("t_LAB4_3.vcd");
    $dumpvars(0, t_LAB4_3);
end

endmodule // t_LAB4_3

數位系統實習/LAB4/LAB4_3.vcd
$date
	Thu Sep 25 12:51:27 2025
$end
$version
	Icarus Verilog
$end
$timescale
	1ps
$end
$scope module t_LAB4_3 $end
$var wire 4 ! D_out [3:0] $end
$var reg 4 " D_in [3:0] $end
$var reg 1 # clk $end
$var reg 1 $ load $end
$var reg 1 % rst $end
$scope module i1 $end
$var wire 4 & D_in [3:0] $end
$var wire 1 # clk $end
$var wire 1 $ load $end
$var wire 1 % rst $end
$var reg 4 ' D_out [3:0] $end
$upscope $end
$upscope $end
$enddefinitions $end
$comment Show the parameter values. $end
$dumpall
$end
#0
$dumpvars
b0 '
b100 &
1%
1$
0#
b100 "
b0 !
$end
#5000
b100 !
b100 '
1#
#10000
0#
0$
#15000
1#
#20000
0#
#25000
1#
#30000
0#
0%
b101 "
b101 &
#35000
b0 !
b0 '
1#
#40000
0#
1%
1$
#45000
b101 !
b101 '
1#
#50000
0#
0$
#55000
1#
#60000
0#
b10 "
b10 &
#65000
1#
#70000
0#
#75000
1#
#80000
0#
#85000
1#
#90000
0#
b100 "
b100 &
1$
#95000
b100 !
b100 '
1#
#100000
0#
#105000
1#
#110000
0#
0$
#115000
1#
#120000
0#
b1100 "
b1100 &
#125000
1#
#130000
0#
#135000
1#
#140000
0#
#145000
1#
#150000
0#
b101 "
b101 &
#155000
1#
#160000
0#
#165000
1#
#170000
0#
#175000
1#
#180000
0#
b10 "
b10 &
