數位邏輯/shift_register/shift_register.v
module shiftregister(output A3,A2,A1,A0,input clk,clear,I3,I2,I1,I0,shift_right,shift_left,S0,S1);
DFF M0(A3,y3,clk,clear);
DFF M1(A2,y2,clk,clear);
DFF M2(A1,y1,clk,clear);
DFF M3(A0,y0,clk,clear);
MUX4x1 M4(y3,S0,S1,I3,A2,shift_right,A3);
MUX4x1 M5(y2,S0,S1,I2,A1,A3,A2);
MUX4x1 M6(y1,S0,S1,I1,A0,A2,A1);
MUX4x1 M7(y0,S0,S1,I0,shift_left,A1,A0);
endmodule
module DFF(output reg Q,input D,clock,clear);
always@(posedge clock,negedge clear)
if(clear==1'b0)
Q<=0;else Q<=D;
endmodule
module MUX4x1(output reg y,input S0,S1,I3,I2,I1,I0);
always@(S0,S1,I3,I2,I1,I0)
case({S0,S1})
2'b00: y<=I0;
2'b01: y<=I1; 
2'b10: y<=I2; 
2'b11: y<=I3; 
endcase
endmodule
module t_shiftregister();
wire [3:0] A_par;
reg [3: 0] In_par;
reg MSB_in, LSB_in;
reg [1:0] s;
reg CLK, Clear_b;
shiftregister M0(A_par[3],A_par[2],A_par[1],A_par[0],CLK, Clear_b, In_par[3],In_par[2],In_par[1],In_par[0],MSB_in, LSB_in,s[0],s[1]);
initial #300 $finish;
initial begin CLK = 0; forever #5 CLK = !CLK; end
initial fork
Clear_b = 0; // Power-up initialization
In_par = 4'b1010; // Word for parallel load; 1010=A
MSB_in = 1'b1; // Bit for serial load
LSB_in = 1'b0; // Bit for serial load
s[1] = 0; s[0] = 0; // Initial action to no change
//
#20 Clear_b = 1; // Running
#40 begin s[1] = 1; s[0] = 1; end // parallel load
#60 Clear_b = 1'b0; // Reset on-the-fly
#80 Clear_b = 1'b1; // Resume action with parallel load at next clock edge
#90 begin s[1] = 0; s[0] = 0; end // No action ¡V register holds 4'b1010
#120 Clear_b = 1'b0; // Clear register
#130 Clear_b = 1'b1;
#140 begin s[1] = 1'b0; s[0] = 1'b1; end // Shifting to right (from MSB)
#170 begin s[1] = 1'b0; s[0] = 1'b0; end // Register should hold 4'b1111
#190 begin Clear_b = 1'b0; s[1] = 1'b0; s[0] = 1'b0; end
#200 begin Clear_b = 1'b1; s[1] = 1'b1; s[0]= 1'b0; end // Resume action ¡V shift left
#230 begin s[1] = 1'b0; s[0] = 1'b0; end
$dumpfile("dump.vcd");
$dumpvars(0,t_shiftregister);
join
endmodule

數位邏輯/shift_register/dump.vcd
$date
	Mon Dec 05 21:41:49 2022
$end
$version
	Icarus Verilog
$end
$timescale
	1s
$end
$scope module t_shiftregister $end
$var wire 4 ! A_par [3:0] $end
$var reg 1 " CLK $end
$var reg 1 # Clear_b $end
$var reg 4 $ In_par [3:0] $end
$var reg 1 % LSB_in $end
$var reg 1 & MSB_in $end
$var reg 2 ' s [1:0] $end
$scope module M0 $end
$var wire 1 ( A0 $end
$var wire 1 ) A1 $end
$var wire 1 * A2 $end
$var wire 1 + A3 $end
$var wire 1 , I0 $end
$var wire 1 - I1 $end
$var wire 1 . I2 $end
$var wire 1 / I3 $end
$var wire 1 0 S0 $end
$var wire 1 1 S1 $end
$var wire 1 2 clear $end
$var wire 1 3 clk $end
$var wire 1 4 shift_left $end
$var wire 1 5 shift_right $end
$var wire 1 6 y0 $end
$var wire 1 7 y1 $end
$var wire 1 8 y2 $end
$var wire 1 9 y3 $end
$scope module M0 $end
$var wire 1 9 D $end
$var wire 1 2 clear $end
$var wire 1 3 clock $end
$var reg 1 : Q $end
$upscope $end
$scope module M1 $end
$var wire 1 8 D $end
$var wire 1 2 clear $end
$var wire 1 3 clock $end
$var reg 1 ; Q $end
$upscope $end
$scope module M2 $end
$var wire 1 7 D $end
$var wire 1 2 clear $end
$var wire 1 3 clock $end
$var reg 1 < Q $end
$upscope $end
$scope module M3 $end
$var wire 1 6 D $end
$var wire 1 2 clear $end
$var wire 1 3 clock $end
$var reg 1 = Q $end
$upscope $end
$scope module M4 $end
$var wire 1 + I0 $end
$var wire 1 5 I1 $end
$var wire 1 * I2 $end
$var wire 1 / I3 $end
$var wire 1 0 S0 $end
$var wire 1 1 S1 $end
$var reg 1 > y $end
$upscope $end
$scope module M5 $end
$var wire 1 * I0 $end
$var wire 1 + I1 $end
$var wire 1 ) I2 $end
$var wire 1 . I3 $end
$var wire 1 0 S0 $end
$var wire 1 1 S1 $end
$var reg 1 ? y $end
$upscope $end
$scope module M6 $end
$var wire 1 ) I0 $end
$var wire 1 * I1 $end
$var wire 1 ( I2 $end
$var wire 1 - I3 $end
$var wire 1 0 S0 $end
$var wire 1 1 S1 $end
$var reg 1 @ y $end
$upscope $end
$scope module M7 $end
$var wire 1 ( I0 $end
$var wire 1 ) I1 $end
$var wire 1 4 I2 $end
$var wire 1 , I3 $end
$var wire 1 0 S0 $end
$var wire 1 1 S1 $end
$var reg 1 A y $end
$upscope $end
$upscope $end
$upscope $end
$enddefinitions $end
#0
$dumpvars
0A
0@
0?
0>
0=
0<
0;
0:
09
08
07
06
15
04
03
02
01
00
1/
0.
1-
0,
0+
0*
0)
0(
b0 '
1&
0%
b1010 $
0#
0"
b0 !
$end
#5
1"
13
#10
0"
03
#15
1"
13
#20
0"
03
1#
12
#25
1"
13
#30
0"
03
#35
1"
13
#40
1@
17
1>
19
10
11
0"
03
b11 '
#45
1<
1)
1:
1+
b1010 !
1"
13
#50
0"
03
#55
1"
13
#60
0<
0)
0:
0+
b0 !
0"
03
0#
02
#65
1"
13
#70
0"
03
#75
1"
13
#80
0"
03
1#
12
#85
1:
1+
1<
1)
b1010 !
1"
13
#90
00
01
0"
03
b0 '
#95
1"
13
#100
0"
03
#105
1"
13
#110
0"
03
#115
1"
13
#120
0>
09
0@
07
0:
0+
0<
0)
b0 !
0"
03
0#
02
#125
1"
13
#130
0"
03
1#
12
#135
1"
13
#140
10
0"
03
b1 '
#145
1"
13
#150
0"
03
#155
1"
13
#160
0"
03
#165
1"
13
#170
00
0"
03
b0 '
#175
1"
13
#180
0"
03
#185
1"
13
#190
0"
03
b0 '
0#
02
#195
1"
13
#200
1>
19
11
0"
03
b10 '
1#
12
#205
1?
18
1:
1+
b1000 !
1"
13
#210
0"
03
#215
1@
17
1;
1*
b1100 !
1"
13
#220
0"
03
#225
1A
16
1<
1)
b1110 !
1"
13
#230
0A
06
01
0"
03
b0 '
