數位邏輯/problem5.28/problem5.28.v
// 
/*module problem5_28(output A,input x,y,clk,reset);
TFF M0(A,w1,clk,reset);
xor(w1,x,y);
endmodule
module TFF(output reg Q,input T,clk,reset);
always@(posedge clk,negedge reset)
if(reset==1'b0)Q<=1'b0;else
case(T)
1'b0: Q<=Q;
1'b1: Q<=!Q;
endcase
endmodule*/
module problem5_28(output reg A,input x,y,clk,reset);
parameter S0=1'b0,S1=1'b1;
xor(w1,x,y);
always@(posedge clk,negedge reset)
if(reset==1'b0)A<=S0;else
case(A)
1'b0: if(w1==1'b0)A<=S0;else A<=S1;
1'b1: if(w1==1'b0)A<=S1;else A<=S0;
endcase
endmodule
module problem5_28_test();
reg x,y,clk,reset;
wire A;
problem5_28 M0(A,x,y,clk,reset);
initial begin clk=1'b0;forever #5 clk=!clk;end
initial fork
#200$finish;
reset=1'b0;
#10 reset=1'b1;
#140 reset=1'b0;
#160 reset=1'b1;
x=1'b0;
#10x=1'b1;
#50x=1'b0;
y=1'b0;
#20y=1'b1;
#70y=1'b0;
#170y=1'b1;
$dumpfile("dump.vcd");
$dumpvars(0,problem5_28_test);
join
endmodule

數位邏輯/problem5.28/dump.vcd
$date
	Sun Dec 11 21:12:45 2022
$end
$version
	Icarus Verilog
$end
$timescale
	1s
$end
$scope module problem5_28_test $end
$var wire 1 ! A $end
$var reg 1 " clk $end
$var reg 1 # reset $end
$var reg 1 $ x $end
$var reg 1 % y $end
$scope module M0 $end
$var wire 1 & clk $end
$var wire 1 ' reset $end
$var wire 1 ( w1 $end
$var wire 1 ) x $end
$var wire 1 * y $end
$var reg 1 + A $end
$upscope $end
$upscope $end
$enddefinitions $end
#0
$dumpvars
0+
0*
0)
0(
0'
0&
0%
0$
0#
0"
0!
$end
#5
1"
1&
#10
1(
0"
0&
1#
1'
1$
1)
#15
1+
1!
1"
1&
#20
0(
0"
0&
1%
1*
#25
1"
1&
#30
0"
0&
#35
1"
1&
#40
0"
0&
#45
1"
1&
#50
1(
0"
0&
0$
0)
#55
0+
0!
1"
1&
#60
0"
0&
#65
1+
1!
1"
1&
#70
0(
0"
0&
0%
0*
#75
1"
1&
#80
0"
0&
#85
1"
1&
#90
0"
0&
#95
1"
1&
#100
0"
0&
#105
1"
1&
#110
0"
0&
#115
1"
1&
#120
0"
0&
#125
1"
1&
#130
0"
0&
#135
1"
1&
#140
0+
0!
0"
0&
0#
0'
#145
1"
1&
#150
0"
0&
#155
1"
1&
#160
0"
0&
1#
1'
#165
1"
1&
#170
1(
0"
0&
1%
1*
#175
1+
1!
1"
1&
#180
0"
0&
#185
0+
0!
1"
1&
#190
0"
0&
#195
1+
1!
1"
1&
